MANIFEST.in
README.rst
setup.cfg
setup.py
docs/index.rst
examples/__init__.py
examples/example.py
generate_captcha/__init__.py
generate_captcha/generate_captcha.py
generate_captcha/msyh.ttf
generate_captcha.egg-info/PKG-INFO
generate_captcha.egg-info/SOURCES.txt
generate_captcha.egg-info/dependency_links.txt
generate_captcha.egg-info/requires.txt
generate_captcha.egg-info/top_level.txt
tests/__init__.py
tests/test.py