Metadata-Version: 1.0
Name: generate-captcha
Version: 0.0.4
Summary: Generate verification code based on Pil library.
Home-page: https://github.com/seekplum/generate_captcha
Author: seekplum
Author-email: 1131909224m@sina.cn
License: GPL-3.0
Keywords: Pil,Captcha,Image
Platform: any
